CEAS/Prob.py
CEAS/R.py
CEAS/annotator.py
CEAS/bigwig_utils.py
CEAS/corelib.py
CEAS/graphics.py
CEAS/inout.py
CEAS/profiler.py
CEAS/sampler.py
CEAS/tables.py
ceas-1.1.2.data/scripts/ChIPAssoc
ceas-1.1.2.data/scripts/build_genomeBG
ceas-1.1.2.data/scripts/ceas
ceas-1.1.2.data/scripts/ceasBW
ceas-1.1.2.data/scripts/gca
ceas-1.1.2.data/scripts/sitepro
ceas-1.1.2.data/scripts/siteproBW
ceas-1.1.2.dist-info/licenses/LICENSE
ceas-1.1.2.dist-info/METADATA
ceas-1.1.2.dist-info/WHEEL
ceas-1.1.2.dist-info/top_level.txt
ceas-1.1.2.dist-info/RECORD
