Metadata-Version: 2.4
Name: CEAS
Version: 1.1.2
Summary: CEAS -- Cis-regulatory Element Annotation System Package (Python3)
Author-email: "Tao Liu (current maintaner" <vladimir.liu@gmail.com>, "H. Gene Shin (original author)" <shin@jimmy.harvard.edu>
License: 
Project-URL: Homepage, http://liulab.dfci.harvard.edu/CEAS/
Classifier: Development Status :: 4 - Beta
Classifier: Environment :: Console
Classifier: Environment :: Web Environment
Classifier: Intended Audience :: Developers
Classifier: License :: OSI Approved :: Artistic License
Classifier: Operating System :: MacOS :: MacOS X
Classifier: Operating System :: Microsoft :: Windows
Classifier: Operating System :: POSIX
Classifier: Programming Language :: Python
Classifier: Topic :: Database
Requires-Python: >=3
License-File: LICENSE
Requires-Dist: bx-python
Dynamic: license-file
